devpytools/__init__.py
devpytools/cacher/__init__.py
devpytools/cacher/cache_provider.py
devpytools/cacher/cacher.py
devpytools/cacher/extensions.py
devpytools/cacher/general.py
devpytools/other/__init__.py
devpytools/other/replace.py
devpytools-0.1.0.dev8.dist-info/LICENSE
devpytools-0.1.0.dev8.dist-info/METADATA
devpytools-0.1.0.dev8.dist-info/WHEEL
devpytools-0.1.0.dev8.dist-info/top_level.txt
devpytools-0.1.0.dev8.dist-info/RECORD
