Metadata-Version: 2.1
Name: devpytools
Version: 0.1.0.dev8
Summary: Various dev tools.
Home-page: https://github.com/glowlex/devpytools
Author: glowlex
Author-email: antonioavocado777@gmail.com
License: MIT
Keywords: tools,cache,dev
Classifier: Development Status :: 4 - Beta
Classifier: Intended Audience :: Developers
Classifier: License :: OSI Approved :: MIT License
Classifier: Operating System :: OS Independent
Classifier: Programming Language :: Python :: 3
Classifier: Programming Language :: Python :: 3.8
Classifier: Programming Language :: Python :: 3.9
Classifier: Programming Language :: Python :: 3.10
Classifier: Programming Language :: Python :: 3.11
Classifier: Programming Language :: Python :: Implementation
Classifier: Topic :: Software Development
Classifier: Topic :: Software Development :: Libraries
Classifier: Topic :: Software Development :: Libraries :: Python Modules
License-File: LICENSE
Requires-Dist: pydashlite
Requires-Dist: typing-extensions
